superkernel/__init__.py
superkernel/main.py
superkernel-0.1.0.dist-info/METADATA
superkernel-0.1.0.dist-info/WHEEL
superkernel-0.1.0.dist-info/top_level.txt
superkernel-0.1.0.dist-info/RECORD
