Metadata-Version: 2.2
Name: superkernel
Version: 0.1.0
Summary: A minimal Python package that prints Hello World
Home-page: https://gitcode.com/cann/graph-infra
Author: graph-infra-community
Author-email: joozhan@163.com
Classifier: Programming Language :: Python :: 3
Classifier: License :: OSI Approved :: MIT License
Classifier: Operating System :: OS Independent
Requires-Python: >=3.8
Dynamic: author
Dynamic: author-email
Dynamic: classifier
Dynamic: description
Dynamic: description-content-type
Dynamic: home-page
Dynamic: requires-python
Dynamic: summary
